red_connector_ftp/__init__.py
red_connector_ftp/commons/__init__.py
red_connector_ftp/commons/cli_modes.py
red_connector_ftp/commons/helpers.py
red_connector_ftp/commons/schemas.py
red_connector_ftp/ftp/__init__.py
red_connector_ftp/ftp/__main__.py
red_connector_ftp/ftp/main.py
red_connector_ftp/ftp/send_receive_dir.py
red_connector_ftp/ftp/send_receive_file.py
red_connector_ftp/ftp_archive/__init__.py
red_connector_ftp/ftp_archive/__main__.py
red_connector_ftp/ftp_archive/main.py
red_connector_ftp/ftp_archive/receive_dir.py
red_connector_ftp/version.py
red_connector_ftp-1.2.dist-info/LICENSE
red_connector_ftp-1.2.dist-info/METADATA
red_connector_ftp-1.2.dist-info/WHEEL
red_connector_ftp-1.2.dist-info/entry_points.txt
red_connector_ftp-1.2.dist-info/RECORD
