Metadata-Version: 2.1
Name: red-connector-ftp
Version: 1.2
Summary: RED Connector FTP is part of the Curious Containers project.
Home-page: https://www.curious-containers.cc/
License: AGPL-3.0
Author: Bruno Schilling
Author-email: Bruno.Schilling@student.htw-berlin.de
Requires-Python: >=3.6,<4.0
Classifier: License :: OSI Approved :: GNU Affero General Public License v3
Classifier: Programming Language :: Python :: 3
Classifier: Programming Language :: Python :: 3.6
Classifier: Programming Language :: Python :: 3.7
Classifier: Programming Language :: Python :: 3.8
Classifier: Programming Language :: Python :: 3.9
Classifier: Programming Language :: Python :: 3.10
Classifier: Programming Language :: Python :: 3.11
Requires-Dist: ftputil (>=5.0.4,<6.0.0)
Requires-Dist: jsonschema (>=3.0,<4.0)
Project-URL: Repository, https://github.com/curious-containers/red-connector-ftp
